LICENSE.md
MANIFEST.in
README.md
setup.py
batty/__init__.py
batty/batty.py
batty/pybat.jl
batty.egg-info/PKG-INFO
batty.egg-info/SOURCES.txt
batty.egg-info/dependency_links.txt
batty.egg-info/requires.txt
batty.egg-info/top_level.txt