Metadata-Version: 2.1
Name: batty
Version: 0.1.0
Summary: BAT to Python
Home-page: https://github.com/philippeller/batty
Author: Philipp Eller
Author-email: peller.phys@gmail.com
License: MIT
Platform: UNKNOWN
Requires-Python: >=3.6
License-File: LICENSE.md
